pitop/keyboard/__init__.py
pitop/keyboard/keyboard_button.py
pitop/keyboard/vendor/__init__.py
pitop/keyboard/vendor/pynput/LICENSE
pitop/keyboard/vendor/pynput/README.md
pitop/keyboard/vendor/pynput/__init__.py
pitop/keyboard/vendor/pynput/_info.py
pitop/keyboard/vendor/pynput/_logger.py
pitop/keyboard/vendor/pynput/_util/__init__.py
pitop/keyboard/vendor/pynput/_util/darwin.py
pitop/keyboard/vendor/pynput/_util/win32.py
pitop/keyboard/vendor/pynput/_util/win32_vks.py
pitop/keyboard/vendor/pynput/_util/xorg.py
pitop/keyboard/vendor/pynput/_util/xorg_keysyms.py
pitop/keyboard/vendor/pynput/keyboard/__init__.py
pitop/keyboard/vendor/pynput/keyboard/_base.py
pitop/keyboard/vendor/pynput/keyboard/_darwin.py
pitop/keyboard/vendor/pynput/keyboard/_win32.py
pitop/keyboard/vendor/pynput/keyboard/_xorg.py
pitop/keyboard/vendor/pynput/mouse/__init__.py
pitop/keyboard/vendor/pynput/mouse/_base.py
pitop/keyboard/vendor/pynput/mouse/_darwin.py
pitop/keyboard/vendor/pynput/mouse/_win32.py
pitop/keyboard/vendor/pynput/mouse/_xorg.py
pitop.keyboard-0.34.3.post1.dist-info/METADATA
pitop.keyboard-0.34.3.post1.dist-info/WHEEL
pitop.keyboard-0.34.3.post1.dist-info/top_level.txt
pitop.keyboard-0.34.3.post1.dist-info/RECORD
